.travis.yml
AUTHORS.rst
CHANGELOG.rst
CONTRIBUTING.rst
ChangeLog
LICENSE
MANIFEST.in
Makefile
README.rst
requirements.txt
setup.cfg
setup.py
tox.ini
sshless/__init__.py
sshless/__main__.py
sshless/cli.py
sshless/core.py
sshless/util.py
sshless.egg-info/PKG-INFO
sshless.egg-info/SOURCES.txt
sshless.egg-info/dependency_links.txt
sshless.egg-info/entry_points.txt
sshless.egg-info/not-zip-safe
sshless.egg-info/pbr.json
sshless.egg-info/requires.txt
sshless.egg-info/top_level.txt
test/DOC.rst
test/README.rst
test/conftest.py
test/test_cli.py
test/test_core_sshless.py
test/test_util.py
test/cassettes/test_cmd_with_instances_ids[sshless_cmd0].yaml
test/cassettes/test_list_commands[7ce628a4-e96c-4a52-88be-027750b6bf58].yaml
test/cassettes/test_list_commands[empty].yaml
test/cassettes/test_list_commands_ok[7ce628a4-e96c-4a52-88be-027750b6bf58].yaml
test/cassettes/test_list_commands_ok[empty].yaml
test/resources/diagram.png
test/terraform/azure.tf
test/terraform/ec2.tf
test/terraform/iam-service.tf
test/terraform/iam.tf
test/terraform/legacy.tf
test/terraform/main.tf
test/terraform/run.sh
test/terraform/ssm.tf
test/terraform/user_data.tpl
test/terraform/vpc.bak
test/terraform/vpc.tf