Metadata-Version: 1.1
Name: sshless
Version: 1.0.1
Summary: sshless using AWS SSM
Home-page: UNKNOWN
Author: cloudreach
Author-email: oss@cloudreach.com
License: UNKNOWN
Platform: UNKNOWN
Classifier: Development Status :: 4 - Beta
Classifier: Intended Audience :: Developers
Classifier: Natural Language :: English
Classifier: Environment :: Console
Classifier: Programming Language :: Python :: 2.6
Classifier: Programming Language :: Python :: 2.7
Classifier: Programming Language :: Python :: 3.6
